Metadata-Version: 1.0
Name: capacities-utilities
Version: 0.1
Summary: Quaternion multiplication and SO(4)
Home-page: UNKNOWN
Author: UNKNOWN
Author-email: mpzedike@go.olemiss.edu
License: UNKNOWN
Platform: UNKNOWN
